langgate/transform/__init__.py
langgate/transform/local.py
langgate/transform/protocol.py
langgate/transform/py.typed
langgate/transform/transformer.py
langgate_transform-0.3.3.dist-info/METADATA
langgate_transform-0.3.3.dist-info/WHEEL
langgate_transform-0.3.3.dist-info/RECORD
