Metadata-Version: 2.4
Name: langgate-transform
Version: 0.3.3
Summary: Parameter transformation utilities for LangGate
Author: Tanantor Ltd.
Maintainer-email: Saran Connoly <saran@tanantor.com>
License: MIT
Requires-Python: >=3.13
Requires-Dist: langgate-core==0.3.3
Requires-Dist: pyyaml<7.0.0,>=6.0.1
